LICENSE
README.rst
setup.py
pfdo/__init__.py
pfdo/__main__.py
pfdo/pfdo.py
pfdo.egg-info/PKG-INFO
pfdo.egg-info/SOURCES.txt
pfdo.egg-info/dependency_links.txt
pfdo.egg-info/entry_points.txt
pfdo.egg-info/not-zip-safe
pfdo.egg-info/requires.txt
pfdo.egg-info/top_level.txt