Metadata-Version: 2.1
Name: pfdo
Version: 3.2.0
Summary: Base machinery for performing operations on pftrees
Home-page: https://github.com/FNNDSC/pfdo
Author: FNNDSC
Author-email: dev@babymri.org
License: MIT
Platform: UNKNOWN
License-File: LICENSE
